Metadata-Version: 2.1
Name: gmKriger
Version: 0.2.0
Summary: Kriging-based ground motion intensity measure calculator.
Home-page: https://github.com/RPretellD/gmKriger
Author: A. Renmin Pretell Ductram
Author-email: rpretell@unr.edu
License: MIT
Keywords: ground motion,Kriging,interpolation
Classifier: Programming Language :: Python :: 3
Classifier: License :: OSI Approved :: MIT License
Requires-Python: >=3.6
License-File: LICENSE
Requires-Dist: numpy
